main.py
setup.py
cryostar.egg-info/PKG-INFO
cryostar.egg-info/SOURCES.txt
cryostar.egg-info/dependency_links.txt
cryostar.egg-info/requires.txt
cryostar.egg-info/top_level.txt